{
	"name": "Event sheet 1",
	"events": [
		{
			"eventType": "variable",
			"name": "credit",
			"type": "number",
			"initialValue": "10",
			"comment": "",
			"isStatic": false,
			"isConstant": false,
			"sid": 995440368135159
		},
		{
			"eventType": "variable",
			"name": "startBlocked",
			"type": "boolean",
			"initialValue": "false",
			"comment": "",
			"isStatic": false,
			"isConstant": false,
			"sid": 436000906928924
		},
		{
			"eventType": "block",
			"conditions": [
				{
					"id": "cursor-is-over-object",
					"objectClass": "Mouse",
					"sid": 891797545967736,
					"parameters": {
						"object": "pusher"
					}
				},
				{
					"id": "mouse-button-is-down",
					"objectClass": "Mouse",
					"sid": 748032842408734,
					"parameters": {
						"mouse-button": "left"
					}
				},
				{
					"id": "compare-boolean-eventvar",
					"objectClass": "System",
					"sid": 376228595966426,
					"parameters": {
						"variable": "startBlocked"
					}
				}
			],
			"actions": [],
			"sid": 701766599541374,
			"children": [
				{
					"eventType": "block",
					"conditions": [
						{
							"id": "every-x-seconds",
							"objectClass": "System",
							"sid": 563150673332792,
							"parameters": {
								"interval-seconds": "0.1"
							}
						}
					],
					"actions": [
						{
							"id": "add-to-instvar",
							"objectClass": "pusher",
							"sid": 688238318734894,
							"parameters": {
								"instance-variable": "power",
								"value": "0.2"
							}
						}
					],
					"sid": 155498964090891
				}
			]
		},
		{
			"eventType": "block",
			"conditions": [
				{
					"id": "on-button-released",
					"objectClass": "Mouse",
					"sid": 352734271981745,
					"parameters": {
						"mouse-button": "left"
					}
				}
			],
			"actions": [
				{
					"id": "set-animation",
					"objectClass": "hand",
					"sid": 352485234953290,
					"parameters": {
						"animation": "\"pressed\"",
						"from": "beginning"
					}
				},
				{
					"id": "wait",
					"objectClass": "System",
					"sid": 354842930357623,
					"parameters": {
						"seconds": "0.25",
						"use-timescale": true
					}
				},
				{
					"id": "set-animation",
					"objectClass": "hand",
					"sid": 313495162581539,
					"parameters": {
						"animation": "\"idle\"",
						"from": "beginning"
					}
				}
			],
			"sid": 486005217810853,
			"children": [
				{
					"eventType": "block",
					"conditions": [
						{
							"id": "cursor-is-over-object",
							"objectClass": "Mouse",
							"sid": 976815307784919,
							"parameters": {
								"object": "pusher"
							}
						},
						{
							"id": "is-boolean-instance-variable-set",
							"objectClass": "coint",
							"sid": 943220570174697,
							"parameters": {
								"instance-variable": "pushed"
							},
							"isInverted": true
						}
					],
					"actions": [
						{
							"id": "apply-impulse-towards-position",
							"objectClass": "coint",
							"sid": 683211913688126,
							"behaviorType": "Physics",
							"parameters": {
								"impulse": "pusher.power",
								"x": "forceTarget.X",
								"y": "forceTarget.Y",
								"image-point": "0"
							}
						},
						{
							"id": "wait",
							"objectClass": "System",
							"sid": 837915529562014,
							"parameters": {
								"seconds": "0.5",
								"use-timescale": true
							}
						},
						{
							"id": "set-instvar-value",
							"objectClass": "pusher",
							"sid": 676669489858277,
							"parameters": {
								"instance-variable": "power",
								"value": "1"
							}
						}
					],
					"sid": 131827698829122
				},
				{
					"eventType": "block",
					"conditions": [
						{
							"id": "else",
							"objectClass": "System",
							"sid": 135496321035003
						}
					],
					"actions": [
						{
							"id": "set-animation",
							"objectClass": "hand",
							"sid": 434733305327075,
							"parameters": {
								"animation": "\"idle\"",
								"from": "beginning"
							}
						}
					],
					"sid": 681476606042003
				}
			]
		},
		{
			"eventType": "block",
			"conditions": [
				{
					"id": "every-tick",
					"objectClass": "System",
					"sid": 744721947682496
				}
			],
			"actions": [
				{
					"id": "set-text",
					"objectClass": "powerVariable",
					"sid": 823142353414541,
					"parameters": {
						"text": "pusher.power"
					}
				},
				{
					"id": "set-text",
					"objectClass": "pointsText",
					"sid": 779304244563110,
					"parameters": {
						"text": "credit"
					}
				}
			],
			"sid": 897020211578799
		},
		{
			"eventType": "block",
			"conditions": [
				{
					"id": "is-overlapping-another-object",
					"objectClass": "coint",
					"sid": 560402328190294,
					"parameters": {
						"object": "coinStart"
					}
				}
			],
			"actions": [
				{
					"id": "set-boolean-eventvar",
					"objectClass": "System",
					"sid": 166428928962454,
					"parameters": {
						"variable": "startBlocked",
						"value": "true"
					}
				}
			],
			"sid": 876579085364168
		},
		{
			"eventType": "block",
			"conditions": [
				{
					"id": "else",
					"objectClass": "System",
					"sid": 258387865593940
				}
			],
			"actions": [
				{
					"id": "set-boolean-eventvar",
					"objectClass": "System",
					"sid": 822349383950623,
					"parameters": {
						"variable": "startBlocked",
						"value": "false"
					}
				}
			],
			"sid": 936854486004547
		},
		{
			"eventType": "block",
			"conditions": [
				{
					"id": "on-key-pressed",
					"objectClass": "Keyboard",
					"sid": 178215972937999,
					"disabled": true,
					"parameters": {
						"key": 82
					}
				},
				{
					"id": "compare-boolean-eventvar",
					"objectClass": "System",
					"sid": 884930422315615,
					"parameters": {
						"variable": "startBlocked"
					},
					"isInverted": true
				},
				{
					"id": "compare-two-values",
					"objectClass": "System",
					"sid": 777828129705434,
					"parameters": {
						"first-value": "credit",
						"comparison": 5,
						"second-value": "1"
					}
				}
			],
			"actions": [
				{
					"id": "create-object",
					"objectClass": "System",
					"sid": 589591904941022,
					"parameters": {
						"object-to-create": "coint",
						"layer": "\"action\"",
						"x": "1350",
						"y": "359",
						"create-hierarchy": false,
						"template-name": "\"\""
					}
				},
				{
					"id": "subtract-from-eventvar",
					"objectClass": "System",
					"sid": 917237052724226,
					"parameters": {
						"variable": "credit",
						"value": "1"
					}
				}
			],
			"sid": 449176995056915,
			"children": [
				{
					"eventType": "block",
					"conditions": [],
					"actions": [],
					"sid": 673466769713179
				}
			]
		},
		{
			"eventType": "block",
			"conditions": [
				{
					"id": "is-overlapping-another-object",
					"objectClass": "coint",
					"sid": 348822788812521,
					"parameters": {
						"object": "forceTarget"
					}
				},
				{
					"id": "trigger-once-while-true",
					"objectClass": "System",
					"sid": 701082909490933
				}
			],
			"actions": [
				{
					"id": "set-boolean-instvar",
					"objectClass": "coint",
					"sid": 101919644871825,
					"parameters": {
						"instance-variable": "pushed",
						"value": "true"
					}
				}
			],
			"sid": 663295233503258
		},
		{
			"eventType": "block",
			"conditions": [
				{
					"id": "for-each",
					"objectClass": "System",
					"sid": 157867411405385,
					"parameters": {
						"object": "coint"
					}
				}
			],
			"actions": [],
			"sid": 250787123335730,
			"children": [
				{
					"eventType": "block",
					"conditions": [
						{
							"id": "is-overlapping-another-object",
							"objectClass": "coint",
							"sid": 292675430169365,
							"parameters": {
								"object": "pointsTrigger"
							}
						}
					],
					"actions": [
						{
							"id": "add-to-eventvar",
							"objectClass": "System",
							"sid": 231028414230777,
							"parameters": {
								"variable": "credit",
								"value": "1"
							}
						},
						{
							"id": "destroy",
							"objectClass": "coint",
							"sid": 974804065603335
						}
					],
					"sid": 145078246903446,
					"children": [
						{
							"eventType": "block",
							"conditions": [
								{
									"id": "compare-instance-variable",
									"objectClass": "slotLights",
									"sid": 270648595141026,
									"parameters": {
										"instance-variable": "slotLightsID",
										"comparison": 0,
										"value": "pointsTrigger.pointsTriggerID"
									}
								}
							],
							"actions": [],
							"sid": 546698861913387,
							"children": [
								{
									"eventType": "block",
									"conditions": [
										{
											"id": "compare-instance-variable",
											"objectClass": "slotLights",
											"sid": 631245006382610,
											"parameters": {
												"instance-variable": "lights",
												"comparison": 2,
												"value": "3"
											}
										}
									],
									"actions": [
										{
											"id": "add-to-instvar",
											"objectClass": "slotLights",
											"sid": 496598304468286,
											"parameters": {
												"instance-variable": "lights",
												"value": "1"
											}
										}
									],
									"sid": 877063750244406,
									"children": [
										{
											"eventType": "block",
											"conditions": [],
											"actions": [
												{
													"id": "set-animation",
													"objectClass": "slotLights",
													"sid": 465399963591250,
													"parameters": {
														"animation": "str(slotLights.lights)",
														"from": "beginning"
													}
												}
											],
											"sid": 557234439667783
										}
									]
								}
							]
						}
					]
				},
				{
					"eventType": "block",
					"conditions": [
						{
							"id": "is-overlapping-another-object",
							"objectClass": "coint",
							"sid": 125911579408666,
							"parameters": {
								"object": "pointsTriggerBottom"
							}
						}
					],
					"actions": [
						{
							"id": "add-to-eventvar",
							"objectClass": "System",
							"sid": 782038937270250,
							"parameters": {
								"variable": "credit",
								"value": "1"
							}
						},
						{
							"id": "destroy",
							"objectClass": "coint",
							"sid": 952565243221980
						}
					],
					"sid": 627736818011102
				}
			]
		},
		{
			"eventType": "block",
			"conditions": [
				{
					"id": "trigger-once-while-true",
					"objectClass": "System",
					"sid": 580599850210121
				}
			],
			"actions": [
				{
					"id": "spawn-another-object",
					"objectClass": "slotWalls",
					"sid": 124348661177730,
					"parameters": {
						"object": "pointsTrigger",
						"layer": "\"background\"",
						"image-point": "\"pointsTrigger\"",
						"create-hierarchy": false,
						"template-name": "\"\""
					}
				},
				{
					"id": "set-instvar-value",
					"objectClass": "pointsTrigger",
					"sid": 692310896687578,
					"parameters": {
						"instance-variable": "pointsTriggerID",
						"value": "slotWalls.slotID"
					}
				},
				{
					"id": "spawn-another-object",
					"objectClass": "slotWalls",
					"sid": 480046391732393,
					"parameters": {
						"object": "slotLights",
						"layer": "\"foreground\"",
						"image-point": "\"slotLights\"",
						"create-hierarchy": false,
						"template-name": "\"\""
					}
				},
				{
					"id": "set-instvar-value",
					"objectClass": "slotLights",
					"sid": 609843537817403,
					"parameters": {
						"instance-variable": "slotLightsID",
						"value": "slotWalls.slotID"
					}
				},
				{
					"type": "script",
					"language": "javascript",
					"script": [
						"const triggers = runtime.objects[\"pointsTrigger\"].getAllInstances();",
						"",
						"for(let i = 0; i<triggers.length; i++) {",
						"\tconsole.log(triggers[i].instVars.pointsTriggerID)",
						"}",
						"",
						"",
						"",
						""
					]
				},
				{
					"id": "spawn-another-object",
					"objectClass": "slotWalls",
					"sid": 734721900414490,
					"parameters": {
						"object": "coinSlotForeground",
						"layer": "\"foreground\"",
						"image-point": "\"coinSlotForeground\"",
						"create-hierarchy": false,
						"template-name": "\"\""
					}
				}
			],
			"sid": 111222728619009
		},
		{
			"eventType": "block",
			"conditions": [
				{
					"id": "is-animation-playing",
					"objectClass": "slotLights",
					"sid": 616185425147941,
					"parameters": {
						"animation": "\"3\""
					}
				},
				{
					"id": "compare-instance-variable",
					"objectClass": "hatch",
					"sid": 294911523599026,
					"parameters": {
						"instance-variable": "hatchID",
						"comparison": 0,
						"value": "slotLights.slotLightsID"
					}
				}
			],
			"actions": [
				{
					"id": "destroy",
					"objectClass": "hatch",
					"sid": 463845217303056,
					"disabled": true
				},
				{
					"id": "set-enabled",
					"objectClass": "hatch",
					"sid": 325505033225149,
					"behaviorType": "Physics",
					"parameters": {
						"mode": "disabled"
					}
				},
				{
					"id": "wait",
					"objectClass": "System",
					"sid": 840754849112542,
					"parameters": {
						"seconds": "3",
						"use-timescale": true
					}
				},
				{
					"id": "set-animation",
					"objectClass": "slotLights",
					"sid": 804219164152924,
					"parameters": {
						"animation": "\"0\"",
						"from": "beginning"
					}
				},
				{
					"id": "set-instvar-value",
					"objectClass": "slotLights",
					"sid": 169009457262092,
					"parameters": {
						"instance-variable": "lights",
						"value": "0"
					}
				},
				{
					"id": "set-enabled",
					"objectClass": "hatch",
					"sid": 305047204678507,
					"behaviorType": "Physics",
					"parameters": {
						"mode": "enabled"
					}
				}
			],
			"sid": 342563848376395,
			"children": [
				{
					"eventType": "block",
					"conditions": [],
					"actions": [],
					"sid": 862769951477664
				}
			]
		},
		{
			"eventType": "block",
			"conditions": [
				{
					"id": "on-key-pressed",
					"objectClass": "Keyboard",
					"sid": 868486101691229,
					"parameters": {
						"key": 84
					}
				}
			],
			"actions": [
				{
					"id": "add-to-eventvar",
					"objectClass": "System",
					"sid": 984239396649134,
					"parameters": {
						"variable": "credit",
						"value": "10"
					}
				}
			],
			"sid": 288675988320068
		}
	],
	"sid": 878535526920507
}