{
	"name": "hackRandMult",
	"plugin-id": "Sprite",
	"sid": 139336301651522,
	"isGlobal": false,
	"editorNewInstanceIsReplica": true,
	"instanceVariables": [],
	"behaviorTypes": [],
	"effectTypes": [],
	"animations": {
		"items": [
			{
				"frames": [
					{
						"width": 162,
						"height": 94,
						"originX": 0,
						"originY": 0,
						"originalSource": "",
						"exportFormat": "lossless",
						"exportQuality": 0.8,
						"fileType": "image/png",
						"imageSpriteId": 5595574,
						"useCollisionPoly": true,
						"duration": 1,
						"tag": ""
					}
				],
				"sid": 787526993663184,
				"name": "shop",
				"isLooping": false,
				"isPingPong": false,
				"repeatCount": 1,
				"repeatTo": 0,
				"speed": 5
			},
			{
				"frames": [
					{
						"width": 162,
						"height": 94,
						"originX": 0,
						"originY": 0,
						"originalSource": "",
						"exportFormat": "lossless",
						"exportQuality": 0.8,
						"fileType": "image/png",
						"imageSpriteId": 3394190,
						"useCollisionPoly": true,
						"duration": 1,
						"tag": ""
					}
				],
				"sid": 280789641193703,
				"name": "slotted",
				"isLooping": false,
				"isPingPong": false,
				"repeatCount": 1,
				"repeatTo": 0,
				"speed": 5
			},
			{
				"frames": [
					{
						"width": 162,
						"height": 94,
						"originX": 0,
						"originY": 0,
						"originalSource": "",
						"exportFormat": "lossless",
						"exportQuality": 0.8,
						"fileType": "image/png",
						"imageSpriteId": 2717798,
						"useCollisionPoly": true,
						"duration": 1,
						"tag": ""
					}
				],
				"sid": 316460944140551,
				"name": "focusedShop",
				"isLooping": false,
				"isPingPong": false,
				"repeatCount": 1,
				"repeatTo": 0,
				"speed": 5
			}
		],
		"subfolders": []
	}
}